[
    {
        "type": "One Change",
        "first_leg": {
            "origin": "Streatham Common Rail Station",
            "destination": "Clapham Junction Rail Station",
            "departure": "06:08",
            "scheduled_departure": "05:55",
            "arrival": "06:16",
            "departurePlatform_Streatham": "TBC",
            "operator": "N/A",
            "status": "On Time"
        },
        "connections": [
            {
                "transferTime": "75 min",
                "second_leg": {
                    "origin": "Clapham Junction Rail Station",
                    "destination": "Imperial Wharf Rail Station",
                    "departure": "07:31",
                    "arrival": "07:35",
                    "departurePlatform_Clapham": "TBC",
                    "operator": "N/A",
                    "status": "On Time"
                }
            },
            {
                "transferTime": "124 min",
                "second_leg": {
                    "origin": "Clapham Junction Rail Station",
                    "destination": "Imperial Wharf Rail Station",
                    "departure": "08:20",
                    "arrival": "08:24",
                    "departurePlatform_Clapham": "TBC",
                    "operator": "N/A",
                    "status": "On Time"
                }
            },
            {
                "transferTime": "136 min",
                "second_leg": {
                    "origin": "Clapham Junction Rail Station",
                    "destination": "Imperial Wharf Rail Station",
                    "departure": "08:32",
                    "arrival": "08:36",
                    "departurePlatform_Clapham": "TBC",
                    "operator": "N/A",
                    "status": "On Time"
                }
            },
            {
                "transferTime": "156 min",
                "second_leg": {
                    "origin": "Clapham Junction Rail Station",
                    "destination": "Imperial Wharf Rail Station",
                    "departure": "08:52",
                    "arrival": "08:56",
                    "departurePlatform_Clapham": "TBC",
                    "operator": "N/A",
                    "status": "On Time"
                }
            },
            {
                "transferTime": "174 min",
                "second_leg": {
                    "origin": "Clapham Junction Rail Station",
                    "destination": "Imperial Wharf Rail Station",
                    "departure": "09:10",
                    "arrival": "09:14",
                    "departurePlatform_Clapham": "TBC",
                    "operator": "N/A",
                    "status": "On Time"
                }
            },
            {
                "transferTime": "179 min",
                "second_leg": {
                    "origin": "Clapham Junction Rail Station",
                    "destination": "Imperial Wharf Rail Station",
                    "departure": "09:15",
                    "arrival": "09:19",
                    "departurePlatform_Clapham": "TBC",
                    "operator": "N/A",
                    "status": "On Time"
                }
            },
            {
                "transferTime": "196 min",
                "second_leg": {
                    "origin": "Clapham Junction Rail Station",
                    "destination": "Imperial Wharf Rail Station",
                    "departure": "09:32",
                    "arrival": "09:36",
                    "departurePlatform_Clapham": "TBC",
                    "operator": "N/A",
                    "status": "On Time"
                }
            },
            {
                "transferTime": "216 min",
                "second_leg": {
                    "origin": "Clapham Junction Rail Station",
                    "destination": "Imperial Wharf Rail Station",
                    "departure": "09:52",
                    "arrival": "09:56",
                    "departurePlatform_Clapham": "TBC",
                    "operator": "N/A",
                    "status": "On Time"
                }
            },
            {
                "transferTime": "236 min",
                "second_leg": {
                    "origin": "Clapham Junction Rail Station",
                    "destination": "Imperial Wharf Rail Station",
                    "departure": "10:12",
                    "arrival": "10:16",
                    "departurePlatform_Clapham": "TBC",
                    "operator": "N/A",
                    "status": "On Time"
                }
            }
        ],
        "totalDuration": "87 min",
        "arrivalTime": "07:35",
        "departureTime": "06:08",
        "segment_id": 1,
        "live_updated_at": "05:32:56"
    },
    {
        "type": "One Change",
        "first_leg": {
            "origin": "Streatham Common Rail Station",
            "destination": "Clapham Junction Rail Station",
            "departure": "06:36",
            "scheduled_departure": "06:36",
            "arrival": "06:47",
            "departurePlatform_Streatham": "TBC",
            "operator": "N/A",
            "status": "On Time"
        },
        "connections": [
            {
                "transferTime": "44 min",
                "second_leg": {
                    "origin": "Clapham Junction Rail Station",
                    "destination": "Imperial Wharf Rail Station",
                    "departure": "07:31",
                    "arrival": "07:35",
                    "departurePlatform_Clapham": "TBC",
                    "operator": "N/A",
                    "status": "On Time"
                }
            },
            {
                "transferTime": "93 min",
                "second_leg": {
                    "origin": "Clapham Junction Rail Station",
                    "destination": "Imperial Wharf Rail Station",
                    "departure": "08:20",
                    "arrival": "08:24",
                    "departurePlatform_Clapham": "TBC",
                    "operator": "N/A",
                    "status": "On Time"
                }
            },
            {
                "transferTime": "105 min",
                "second_leg": {
                    "origin": "Clapham Junction Rail Station",
                    "destination": "Imperial Wharf Rail Station",
                    "departure": "08:32",
                    "arrival": "08:36",
                    "departurePlatform_Clapham": "TBC",
                    "operator": "N/A",
                    "status": "On Time"
                }
            },
            {
                "transferTime": "125 min",
                "second_leg": {
                    "origin": "Clapham Junction Rail Station",
                    "destination": "Imperial Wharf Rail Station",
                    "departure": "08:52",
                    "arrival": "08:56",
                    "departurePlatform_Clapham": "TBC",
                    "operator": "N/A",
                    "status": "On Time"
                }
            },
            {
                "transferTime": "143 min",
                "second_leg": {
                    "origin": "Clapham Junction Rail Station",
                    "destination": "Imperial Wharf Rail Station",
                    "departure": "09:10",
                    "arrival": "09:14",
                    "departurePlatform_Clapham": "TBC",
                    "operator": "N/A",
                    "status": "On Time"
                }
            },
            {
                "transferTime": "148 min",
                "second_leg": {
                    "origin": "Clapham Junction Rail Station",
                    "destination": "Imperial Wharf Rail Station",
                    "departure": "09:15",
                    "arrival": "09:19",
                    "departurePlatform_Clapham": "TBC",
                    "operator": "N/A",
                    "status": "On Time"
                }
            },
            {
                "transferTime": "165 min",
                "second_leg": {
                    "origin": "Clapham Junction Rail Station",
                    "destination": "Imperial Wharf Rail Station",
                    "departure": "09:32",
                    "arrival": "09:36",
                    "departurePlatform_Clapham": "TBC",
                    "operator": "N/A",
                    "status": "On Time"
                }
            },
            {
                "transferTime": "185 min",
                "second_leg": {
                    "origin": "Clapham Junction Rail Station",
                    "destination": "Imperial Wharf Rail Station",
                    "departure": "09:52",
                    "arrival": "09:56",
                    "departurePlatform_Clapham": "TBC",
                    "operator": "N/A",
                    "status": "On Time"
                }
            },
            {
                "transferTime": "205 min",
                "second_leg": {
                    "origin": "Clapham Junction Rail Station",
                    "destination": "Imperial Wharf Rail Station",
                    "departure": "10:12",
                    "arrival": "10:16",
                    "departurePlatform_Clapham": "TBC",
                    "operator": "N/A",
                    "status": "On Time"
                }
            }
        ],
        "totalDuration": "59 min",
        "arrivalTime": "07:35",
        "departureTime": "06:36",
        "segment_id": 2,
        "live_updated_at": "05:32:56"
    },
    {
        "type": "One Change",
        "first_leg": {
            "origin": "Streatham Common Rail Station",
            "destination": "Clapham Junction Rail Station",
            "departure": "07:20",
            "scheduled_departure": "07:20",
            "arrival": "07:30",
            "departurePlatform_Streatham": "TBC",
            "operator": "N/A",
            "status": "On Time"
        },
        "connections": [
            {
                "transferTime": "1 min",
                "second_leg": {
                    "origin": "Clapham Junction Rail Station",
                    "destination": "Imperial Wharf Rail Station",
                    "departure": "07:31",
                    "arrival": "07:35",
                    "departurePlatform_Clapham": "TBC",
                    "operator": "N/A",
                    "status": "On Time"
                }
            },
            {
                "transferTime": "50 min",
                "second_leg": {
                    "origin": "Clapham Junction Rail Station",
                    "destination": "Imperial Wharf Rail Station",
                    "departure": "08:20",
                    "arrival": "08:24",
                    "departurePlatform_Clapham": "TBC",
                    "operator": "N/A",
                    "status": "On Time"
                }
            },
            {
                "transferTime": "62 min",
                "second_leg": {
                    "origin": "Clapham Junction Rail Station",
                    "destination": "Imperial Wharf Rail Station",
                    "departure": "08:32",
                    "arrival": "08:36",
                    "departurePlatform_Clapham": "TBC",
                    "operator": "N/A",
                    "status": "On Time"
                }
            },
            {
                "transferTime": "82 min",
                "second_leg": {
                    "origin": "Clapham Junction Rail Station",
                    "destination": "Imperial Wharf Rail Station",
                    "departure": "08:52",
                    "arrival": "08:56",
                    "departurePlatform_Clapham": "TBC",
                    "operator": "N/A",
                    "status": "On Time"
                }
            },
            {
                "transferTime": "100 min",
                "second_leg": {
                    "origin": "Clapham Junction Rail Station",
                    "destination": "Imperial Wharf Rail Station",
                    "departure": "09:10",
                    "arrival": "09:14",
                    "departurePlatform_Clapham": "TBC",
                    "operator": "N/A",
                    "status": "On Time"
                }
            },
            {
                "transferTime": "105 min",
                "second_leg": {
                    "origin": "Clapham Junction Rail Station",
                    "destination": "Imperial Wharf Rail Station",
                    "departure": "09:15",
                    "arrival": "09:19",
                    "departurePlatform_Clapham": "TBC",
                    "operator": "N/A",
                    "status": "On Time"
                }
            },
            {
                "transferTime": "122 min",
                "second_leg": {
                    "origin": "Clapham Junction Rail Station",
                    "destination": "Imperial Wharf Rail Station",
                    "departure": "09:32",
                    "arrival": "09:36",
                    "departurePlatform_Clapham": "TBC",
                    "operator": "N/A",
                    "status": "On Time"
                }
            },
            {
                "transferTime": "142 min",
                "second_leg": {
                    "origin": "Clapham Junction Rail Station",
                    "destination": "Imperial Wharf Rail Station",
                    "departure": "09:52",
                    "arrival": "09:56",
                    "departurePlatform_Clapham": "TBC",
                    "operator": "N/A",
                    "status": "On Time"
                }
            },
            {
                "transferTime": "162 min",
                "second_leg": {
                    "origin": "Clapham Junction Rail Station",
                    "destination": "Imperial Wharf Rail Station",
                    "departure": "10:12",
                    "arrival": "10:16",
                    "departurePlatform_Clapham": "TBC",
                    "operator": "N/A",
                    "status": "On Time"
                }
            }
        ],
        "totalDuration": "15 min",
        "arrivalTime": "07:35",
        "departureTime": "07:20",
        "segment_id": 3,
        "live_updated_at": "05:32:56"
    }
]