[
    {
        "type": "One Change",
        "first_leg": {
            "origin": "Streatham Common Rail Station",
            "destination": "Clapham Junction Rail Station",
            "departure": "23:20",
            "scheduled_departure": "23:20",
            "arrival": "23:31",
            "departurePlatform_Streatham": "TBC",
            "operator": "N/A",
            "status": "On Time"
        },
        "connections": [
            {
                "transferTime": "332 min",
                "second_leg": {
                    "origin": "Clapham Junction Rail Station",
                    "destination": "Imperial Wharf Rail Station",
                    "departure": "05:03",
                    "arrival": "05:07",
                    "departurePlatform_Clapham": "TBC",
                    "operator": "N/A",
                    "status": "On Time"
                }
            },
            {
                "transferTime": "382 min",
                "second_leg": {
                    "origin": "Clapham Junction Rail Station",
                    "destination": "Imperial Wharf Rail Station",
                    "departure": "05:53",
                    "arrival": "05:58",
                    "departurePlatform_Clapham": "TBC",
                    "operator": "N/A",
                    "status": "On Time"
                }
            },
            {
                "transferTime": "389 min",
                "second_leg": {
                    "origin": "Clapham Junction Rail Station",
                    "destination": "Imperial Wharf Rail Station",
                    "departure": "06:00",
                    "arrival": "06:04",
                    "departurePlatform_Clapham": "TBC",
                    "operator": "N/A",
                    "status": "On Time"
                }
            },
            {
                "transferTime": "398 min",
                "second_leg": {
                    "origin": "Clapham Junction Rail Station",
                    "destination": "Imperial Wharf Rail Station",
                    "departure": "06:09",
                    "arrival": "06:13",
                    "departurePlatform_Clapham": "TBC",
                    "operator": "N/A",
                    "status": "On Time"
                }
            },
            {
                "transferTime": "412 min",
                "second_leg": {
                    "origin": "Clapham Junction Rail Station",
                    "destination": "Imperial Wharf Rail Station",
                    "departure": "06:23",
                    "arrival": "06:27",
                    "departurePlatform_Clapham": "TBC",
                    "operator": "N/A",
                    "status": "On Time"
                }
            },
            {
                "transferTime": "422 min",
                "second_leg": {
                    "origin": "Clapham Junction Rail Station",
                    "destination": "Imperial Wharf Rail Station",
                    "departure": "06:33",
                    "arrival": "06:37",
                    "departurePlatform_Clapham": "TBC",
                    "operator": "N/A",
                    "status": "On Time"
                }
            },
            {
                "transferTime": "21 min",
                "second_leg": {
                    "origin": "Clapham Junction Rail Station",
                    "destination": "Imperial Wharf Rail Station",
                    "departure": "23:52",
                    "arrival": "23:56",
                    "departurePlatform_Clapham": "TBC",
                    "operator": "N/A",
                    "status": "On Time"
                }
            }
        ],
        "totalDuration": "347 min",
        "arrivalTime": "05:07",
        "departureTime": "23:20",
        "segment_id": 1,
        "live_updated_at": "22:56:00"
    }
]