[
    {
        "type": "One Change",
        "departureTime": "07:38",
        "arrivalTime": "08:18",
        "totalDuration": "40 min",
        "status": "On Time",
        "live_updated_at": "06:38:14",
        "legs": [
            {
                "origin": "Streatham Common Rail Station",
                "destination": "Clapham Junction Rail Station",
                "departure": "07:38",
                "arrival": "07:47",
                "departurePlatform_Streatham": "TBC",
                "operator": "N/A",
                "status": "On Time"
            },
            {
                "type": "transfer",
                "location": "Clapham Junction Rail Station",
                "transferTime": "27 min"
            },
            {
                "origin": "Clapham Junction Rail Station",
                "destination": "Imperial Wharf Rail Station",
                "departure": "08:14",
                "arrival": "08:18",
                "departurePlatform_Clapham": "TBC",
                "operator": "N/A",
                "status": "On Time"
            }
        ],
        "id": 1
    },
    {
        "type": "One Change",
        "departureTime": "08:01",
        "arrivalTime": "08:24",
        "totalDuration": "23 min",
        "status": "On Time",
        "live_updated_at": "06:38:14",
        "legs": [
            {
                "origin": "Streatham Common Rail Station",
                "destination": "Clapham Junction Rail Station",
                "departure": "08:01",
                "arrival": "08:06",
                "departurePlatform_Streatham": "TBC",
                "operator": "N/A",
                "status": "On Time"
            },
            {
                "type": "transfer",
                "location": "Clapham Junction Rail Station",
                "transferTime": "14 min"
            },
            {
                "origin": "Clapham Junction Rail Station",
                "destination": "Imperial Wharf Rail Station",
                "departure": "08:20",
                "arrival": "08:24",
                "departurePlatform_Clapham": "TBC",
                "operator": "N/A",
                "status": "On Time"
            }
        ],
        "id": 2
    },
    {
        "type": "One Change",
        "departureTime": "08:21",
        "arrivalTime": "08:48",
        "totalDuration": "27 min",
        "status": "On Time",
        "live_updated_at": "06:38:14",
        "legs": [
            {
                "origin": "Streatham Common Rail Station",
                "destination": "Clapham Junction Rail Station",
                "departure": "08:21",
                "arrival": "08:31",
                "departurePlatform_Streatham": "TBC",
                "operator": "N/A",
                "status": "On Time"
            },
            {
                "type": "transfer",
                "location": "Clapham Junction Rail Station",
                "transferTime": "13 min"
            },
            {
                "origin": "Clapham Junction Rail Station",
                "destination": "Imperial Wharf Rail Station",
                "departure": "08:44",
                "arrival": "08:48",
                "departurePlatform_Clapham": "TBC",
                "operator": "N/A",
                "status": "On Time"
            }
        ],
        "id": 3
    }
]